{"status":"done","publicPath":"/templates/bundle/","chunks":{"404":[{"name":"js/404.js","publicPath":"/templates/bundle/js/404.js","path":"C:\\Users\\Gory\\pycharmprojects\\halo\\templates\\bundle\\js\\404.js"},{"name":"css/404.css","publicPath":"/templates/bundle/css/404.css","path":"C:\\Users\\Gory\\pycharmprojects\\halo\\templates\\bundle\\css\\404.css"}],"500":[{"name":"js/500.js","publicPath":"/templates/bundle/js/500.js","path":"C:\\Users\\Gory\\pycharmprojects\\halo\\templates\\bundle\\js\\500.js"},{"name":"css/500.css","publicPath":"/templates/bundle/css/500.css","path":"C:\\Users\\Gory\\pycharmprojects\\halo\\templates\\bundle\\css\\500.css"}],"leaderboard":[{"name":"js/leaderboard.js","publicPath":"/templates/bundle/js/leaderboard.js","path":"C:\\Users\\Gory\\pycharmprojects\\halo\\templates\\bundle\\js\\leaderboard.js"},{"name":"css/leaderboard.css","publicPath":"/templates/bundle/css/leaderboard.css","path":"C:\\Users\\Gory\\pycharmprojects\\halo\\templates\\bundle\\css\\leaderboard.css"}],"profile":[{"name":"js/profile.js","publicPath":"/templates/bundle/js/profile.js","path":"C:\\Users\\Gory\\pycharmprojects\\halo\\templates\\bundle\\js\\profile.js"},{"name":"css/profile.css","publicPath":"/templates/bundle/css/profile.css","path":"C:\\Users\\Gory\\pycharmprojects\\halo\\templates\\bundle\\css\\profile.css"}],"donate":[{"name":"js/donate.js","publicPath":"/templates/bundle/js/donate.js","path":"C:\\Users\\Gory\\pycharmprojects\\halo\\templates\\bundle\\js\\donate.js"},{"name":"css/donate.css","publicPath":"/templates/bundle/css/donate.css","path":"C:\\Users\\Gory\\pycharmprojects\\halo\\templates\\bundle\\css\\donate.css"}],"home":[{"name":"js/home.js","publicPath":"/templates/bundle/js/home.js","path":"C:\\Users\\Gory\\pycharmprojects\\halo\\templates\\bundle\\js\\home.js"},{"name":"css/home.css","publicPath":"/templates/bundle/css/home.css","path":"C:\\Users\\Gory\\pycharmprojects\\halo\\templates\\bundle\\css\\home.css"}],"vendors":[{"name":"js/vendors.js","publicPath":"/templates/bundle/js/vendors.js","path":"C:\\Users\\Gory\\pycharmprojects\\halo\\templates\\bundle\\js\\vendors.js"},{"name":"css/vendors.css","publicPath":"/templates/bundle/css/vendors.css","path":"C:\\Users\\Gory\\pycharmprojects\\halo\\templates\\bundle\\css\\vendors.css"}]},"error":"unknown-error"}